caddo_data_factory/__init__.py
caddo_data_factory/__main__.py
caddo_data_factory/functions/__init__.py
caddo_data_factory/functions/folding_enum.py
caddo_data_factory/functions/folding_methods.py
caddo_data_factory/functions/folds_preparation.py
caddo_data_factory/functions/functions_loader.py
caddo_data_factory/settings/__init__.py
caddo_data_factory/settings/settings_reader.py
caddo_data_factory-0.10.1.dist-info/METADATA
caddo_data_factory-0.10.1.dist-info/WHEEL
caddo_data_factory-0.10.1.dist-info/top_level.txt
caddo_data_factory-0.10.1.dist-info/RECORD
