Metadata-Version: 2.1
Name: caddo-data-factory
Version: 0.10.1
Summary: Data Factpry for CaddoBenchmark Project
Author-email: Piotr Tylczyński <piotr@ptl.cloud>, Katarzyna Kulesa <katarzyna.kulesa@kasiait.pl>
Classifier: Programming Language :: Python :: 3
Classifier: License :: OSI Approved :: MIT License
Classifier: Operating System :: OS Independent
Requires-Python: >=3.7
Requires-Dist: scikit-learn
Requires-Dist: caddo-file-parser
Requires-Dist: numpy
Requires-Dist: pandas
Requires-Dist: pyyaml
Requires-Dist: scipy
